roboflex/__init__.py
roboflex/dynoflex.py
roboflex/flexbuffers.py
roboflex/flextensors.py
roboflex/roboflex_core_python_ext.cpython-311-darwin.so
roboflex-0.1.38.dist-info/licenses/LICENSE
roboflex-0.1.38.dist-info/METADATA
roboflex-0.1.38.dist-info/WHEEL
roboflex-0.1.38.dist-info/top_level.txt
roboflex-0.1.38.dist-info/RECORD
