Metadata-Version: 2.4
Name: roboflex
Version: 0.1.38
Summary: Roboflex Core Library: a C++20 and python library for distributed robotics and automation.
Home-page: https://github.com/flexrobotics/roboflex
Author: Colin Prepscius
Author-email: colinprepscius@gmail.com
License: MIT
Keywords: robotics,middleware,flexbuffers,python,c++,c++20
Classifier: Intended Audience :: Developers
Classifier: License :: OSI Approved :: MIT License
Classifier: Topic :: Software Development :: Libraries :: Python Modules
Classifier: Topic :: Software Development :: Embedded Systems
Classifier: Framework :: Robot Framework
Classifier: Framework :: Robot Framework :: Library
Classifier: Framework :: Robot Framework :: Tool
Classifier: Programming Language :: C++
Classifier: Programming Language :: Python :: 3
Requires-Python: >=3.6
License-File: LICENSE
Requires-Dist: numpy
Dynamic: author
Dynamic: author-email
Dynamic: classifier
Dynamic: description
Dynamic: description-content-type
Dynamic: home-page
Dynamic: keywords
Dynamic: license
Dynamic: license-file
Dynamic: requires-dist
Dynamic: requires-python
Dynamic: summary
